odoo/addons/website_adv_image_optimization/README.rst
odoo/addons/website_adv_image_optimization/__init__.py
odoo/addons/website_adv_image_optimization/__manifest__.py
odoo/addons/website_adv_image_optimization/controllers/__init__.py
odoo/addons/website_adv_image_optimization/controllers/main.py
odoo/addons/website_adv_image_optimization/i18n/website_adv_image_optimization.pot
odoo/addons/website_adv_image_optimization/readme/CONTRIBUTORS.rst
odoo/addons/website_adv_image_optimization/readme/DESCRIPTION.rst
odoo/addons/website_adv_image_optimization/readme/USAGE.rst
odoo/addons/website_adv_image_optimization/static/description/icon.png
odoo/addons/website_adv_image_optimization/static/description/index.html
odoo/addons/website_adv_image_optimization/static/description/screenshot0.png
odoo/addons/website_adv_image_optimization/static/src/css/website_adv_image_optimization.scss
odoo/addons/website_adv_image_optimization/static/src/js/website_adv_image_optimization.js
odoo/addons/website_adv_image_optimization/static/src/xml/website_adv_image_optimization.xml
odoo/addons/website_adv_image_optimization/templates/assets.xml
odoo/addons/website_adv_image_optimization/tests/__init__.py
odoo/addons/website_adv_image_optimization/tests/test_controller.py
odoo12_addon_website_adv_image_optimization-12.0.1.0.1.dist-info/METADATA
odoo12_addon_website_adv_image_optimization-12.0.1.0.1.dist-info/WHEEL
odoo12_addon_website_adv_image_optimization-12.0.1.0.1.dist-info/top_level.txt
odoo12_addon_website_adv_image_optimization-12.0.1.0.1.dist-info/RECORD
